helix_events_sdk/__init__.py
helix_events_sdk/event_reader.py
helix_events_sdk/event_writer.py
helix_events_sdk/py.typed
helix_events_sdk/events/__init__.py
helix_events_sdk/events/audit.py
helix_events_sdk/schemas/__init__.py
helix_events_sdk/schemas/audit.py
helix_events_sdk/schemas/audit_enums.py
helix_events_sdk/schemas/source.py
tests/__init__.py
tests/test_read_events_from_topic.py
tests/test_send_events.py
tests/common/__init__.py
tests/common/logger.py
helix.events.sdk-0.1.1.dist-info/LICENSE
helix.events.sdk-0.1.1.dist-info/METADATA
helix.events.sdk-0.1.1.dist-info/WHEEL
helix.events.sdk-0.1.1.dist-info/top_level.txt
helix.events.sdk-0.1.1.dist-info/RECORD
