Metadata-Version: 2.1
Name: helix.events.sdk
Version: 0.1.1
Summary: Event SDK for creating Events in the helix architecture
Home-page: https://github.com/icanbwell/helix.events.sdk
Author: Michael Vidal
Author-email: michael.vidal@icanbwell.com
License: Apache 2.0
License-File: LICENSE
Requires-Dist: cloudevents (>=1.2.0)
Requires-Dist: fhir.resources (>=5.0.0)
Requires-Dist: kafka-python (>=2.0.2)
